meow/validators/__init__.py
meow/validators/compat.py
meow/validators/container.py
meow/validators/elements.py
meow/validators/exception.py
meow/validators/py.typed
meow.validators-1.5.1.dist-info/LICENSE
meow.validators-1.5.1.dist-info/METADATA
meow.validators-1.5.1.dist-info/WHEEL
meow.validators-1.5.1.dist-info/top_level.txt
meow.validators-1.5.1.dist-info/RECORD
