Metadata-Version: 2.1
Name: meow.validators
Version: 1.5.1
Summary: Data validation
Home-page: https://github.com/aachurin/meow.validators
Author: Andrey Churin
Maintainer: Andrey Churin
Maintainer-email: aachurin@gmail.com
License: MIT
Platform: UNKNOWN
Classifier: Development Status :: 5 - Production/Stable
Classifier: Environment :: Web Environment
Classifier: Intended Audience :: Developers
Classifier: License :: OSI Approved :: MIT License
Classifier: Operating System :: OS Independent
Classifier: Programming Language :: Python :: 3 :: Only
Classifier: Programming Language :: Python :: 3.8
Classifier: Programming Language :: Python :: 3.9
